sqlfactory/__init__.py
sqlfactory/condition/__init__.py
sqlfactory/condition/base.py
sqlfactory/condition/between.py
sqlfactory/condition/in_condition.py
sqlfactory/condition/like.py
sqlfactory/condition/rlike.py
sqlfactory/condition/simple.py
sqlfactory/delete/__init__.py
sqlfactory/delete/delete.py
sqlfactory/dialect.py
sqlfactory/entities.py
sqlfactory/execute.py
sqlfactory/func/__init__.py
sqlfactory/func/agg.py
sqlfactory/func/base.py
sqlfactory/func/control.py
sqlfactory/func/datetime.py
sqlfactory/func/enc.py
sqlfactory/func/info.py
sqlfactory/func/misc.py
sqlfactory/func/numeric.py
sqlfactory/func/str.py
sqlfactory/insert/__init__.py
sqlfactory/insert/insert.py
sqlfactory/insert/values.py
sqlfactory/logger.py
sqlfactory/mixins/__init__.py
sqlfactory/mixins/join.py
sqlfactory/mixins/limit.py
sqlfactory/mixins/order.py
sqlfactory/mixins/where.py
sqlfactory/py.typed
sqlfactory/select/__init__.py
sqlfactory/select/aliased.py
sqlfactory/select/column_list.py
sqlfactory/select/cte.py
sqlfactory/select/join.py
sqlfactory/select/select.py
sqlfactory/select/union.py
sqlfactory/statement.py
sqlfactory/update/__init__.py
sqlfactory/update/update.py
sqlfactory-1.17.2.dist-info/METADATA
sqlfactory-1.17.2.dist-info/WHEEL
sqlfactory-1.17.2.dist-info/licenses/LICENSE
sqlfactory-1.17.2.dist-info/RECORD
