Metadata-Version: 2.4
Name: sqlfactory
Version: 1.17.2
Summary: Convenient classes for building SQL queries in Python. Main purpose of this library is to ease construction of SQL queries in Python code. It is not an ORM (and don't intend to be), just a plain SQL query builder with syntax as similar to actual SQL as possible.
License: MIT
License-File: LICENSE
Author: Michal Kuchta
Author-email: niximor@gmail.com
Requires-Python: >=3.11,<4.0
Classifier: Development Status :: 5 - Production/Stable
Classifier: Intended Audience :: Developers
Classifier: License :: OSI Approved :: MIT License
Classifier: Operating System :: OS Independent
Classifier: Programming Language :: Python :: 3
Classifier: Programming Language :: Python :: 3.11
Classifier: Programming Language :: Python :: 3.12
Classifier: Programming Language :: Python :: 3.13
Classifier: Programming Language :: Python :: 3.14
Classifier: Programming Language :: SQL
Classifier: Topic :: Database
Classifier: Topic :: Software Development :: Libraries
Project-URL: Documentation, https://gcm-cz.gitlab.io/sqlfactory/
Project-URL: Homepage, https://gitlab.com/gcm-cz/sqlfactory
Project-URL: Issues, https://gitlab.com/gcm-cz/sqlfactory/-/issues
Project-URL: Repository, https://gitlab.com/gcm-cz/sqlfactory
